[
  {
    "ID": 1,
    "Title": "Academic Calendar for Odd Term 2024-25 GEC Patan",
    "IsFile": 1,
    "File": "/js/Academic Calendar/Academic_Calendar_gecpODD.jpg",
    "Date": "2024-10-06",
    "ControllerName": "",
    "ActionName": ""
  },
  {
    "ID": 2,
    "Title": "Academic Calendar for Odd Term 2024-25 CSE Department",
    "IsFile": 1,
    "File": "/images/CampusCommittee/CurrentPlacement/Brevitazplacement.png",
    "Date": "2024-10-06",
    "ControllerName": "",
    "ActionName": ""
  },
  {
    "ID": 3,
    "Title": "Academic Calendar for Odd Term 2024-25 CSE Department",
    "IsFile": 1,
    "File": "/images/CampusCommittee/CurrentPlacement/Brevitazplacement.png",
    "Date": "2024-10-06",
    "ControllerName": "",
    "ActionName": ""
  },
  {
    "ID": 4,
    "Title": "Academic Calendar for Odd Term 2024-25 CSE Department",
    "IsFile": 1,
    "File": "/images/CampusCommittee/CurrentPlacement/Brevitazplacement.png",
    "Date": "2024-10-06",
    "ControllerName": "",
    "ActionName": ""
  }
]